py3status_omegav
