Metadata-Version: 2.1
Name: py3status-omegav
Version: 0.1.1
Summary: py3status module to check door status at Omega Verksted
Home-page: https://github.com/jakoblover/py3status-omegav
License: UNKNOWN
Platform: UNKNOWN
Classifier: Environment :: Console
Classifier: Topic :: Utilities
Classifier: Programming Language :: Python
Classifier: Programming Language :: Python :: 3.7
